py2mql5-0.1.0.dist-info/METADATA
py2mql5-0.1.0.dist-info/WHEEL
py2mql5-0.1.0.dist-info/entry_points.txt
py2mql5-0.1.0.dist-info/licenses/LICENSE
py2mql5/__init__.py
py2mql5-0.1.0.dist-info/RECORD
