Metadata-Version: 2.1
Name: py2mql5
Version: 0.1.0
Summary: A wrapper of MetaTrader5 official package that enables multiple terminal instances at the same time.
Author-Email: pytree <houjunqimail@gmail.com>
License: MIT
Requires-Python: >=3.13
Requires-Dist: MetaTrader5>=5.0.4803
